README.md
setup.cfg
setup.py
distributions/Binomialdistribution.py
distributions/Gaussiandistribution.py
distributions/Generaldistribution.py
distributions/__init__.py
distributions2_chrisrydahl.egg-info/PKG-INFO
distributions2_chrisrydahl.egg-info/SOURCES.txt
distributions2_chrisrydahl.egg-info/dependency_links.txt
distributions2_chrisrydahl.egg-info/not-zip-safe
distributions2_chrisrydahl.egg-info/top_level.txt